katcp/__init__.py
katcp/client.py
katcp/compat.py
katcp/core.py
katcp/fake_clients.py
katcp/inspecting_client.py
katcp/ioloop_manager.py
katcp/kattypes.py
katcp/object_proxies.py
katcp/resource.py
katcp/resource_client.py
katcp/sampling.py
katcp/sensortree.py
katcp/server.py
katcp/testutils.py
katcp/test/__init__.py
katcp/test/test_client.py
katcp/test/test_compat.py
katcp/test/test_core.py
katcp/test/test_fake_clients.py
katcp/test/test_inspecting_client.py
katcp/test/test_ioloop_manager.py
katcp/test/test_katcp_bnf.py
katcp/test/test_kattypes.py
katcp/test/test_resource.py
katcp/test/test_resource_client.py
katcp/test/test_sampling.py
katcp/test/test_sensortree.py
katcp/test/test_server.py
katcp/test/test_testutils.py
scripts/__init__.py
scripts/katcp-exampleclient.py
scripts/katcp-exampleserver.py
katcp-0.9.3.dist-info/LICENSE
katcp-0.9.3.dist-info/METADATA
katcp-0.9.3.dist-info/WHEEL
katcp-0.9.3.dist-info/top_level.txt
katcp-0.9.3.dist-info/RECORD
