Metadata-Version: 2.1
Name: katcp
Version: 0.9.3
Summary: Karoo Array Telescope Communication Protocol library
Home-page: https://github.com/ska-sa/katcp-python
Author: MeerKAT CAM Team
Author-email: cam@ska.ac.za
License: BSD
Download-URL: https://pypi.org/project/katcp/
Keywords: kat kat7 ska MeerKAT
Platform: OS Independent
Classifier: Development Status :: 5 - Production/Stable
Classifier: Intended Audience :: Developers
Classifier: License :: OSI Approved :: BSD License
Classifier: Operating System :: OS Independent
Classifier: Programming Language :: Python
Classifier: Programming Language :: Python :: 2
Classifier: Programming Language :: Python :: 2.7
Classifier: Programming Language :: Python :: 3
Classifier: Programming Language :: Python :: 3.5
Classifier: Programming Language :: Python :: 3.6
Classifier: Programming Language :: Python :: 3.7
Classifier: Programming Language :: Python :: 3.8
Classifier: Topic :: Software Development :: Libraries :: Python Modules
Classifier: Topic :: Scientific/Engineering :: Astronomy
Requires-Python: >=2.7, !=3.0.*, !=3.1.*, !=3.2.*, !=3.3.*, !=3.4.*
Requires-Dist: ply
Requires-Dist: future
Requires-Dist: tornado (<5,>=4.3)
Requires-Dist: futures ; python_version < "3"
